[
  {
    "id": "3NF8u0Heo7YBsIKIpkPp",
    "proId": "Mb9DgsGfQ9aFtJbymTNVGqu0Rgm1",
    "clientId": "LPYvmr6SVhVRYXbzkNFselOxRWG3",
    "dateTime": {
      "_seconds": 1751612400,
      "_nanoseconds": 0
    },
    "duration": 30,
    "timeSlot": "09:00",
    "status": "CONFIRMED",
    "roomId": "128189"
  },
  {
    "id": "cAqY8ekX2wdg3MaC9zO5",
    "proId": "Mb9DgsGfQ9aFtJbymTNVGqu0Rgm1",
    "clientId": "HnVQLhI72sakNZqCMMjxiDM9XQm2",
    "dateTime": {
      "_seconds": 1751616000,
      "_nanoseconds": 0
    },
    "duration": 30,
    "timeSlot": "10:00",
    "status": "CONFIRMED",
    "roomId": "491918"
  },
  {
    "id": "pMQg2IjPy7p8pnSTgFsc",
    "proId": "RD6p6iddC6XggWisjQSfzIkEm782",
    "clientId": "F8nlh9yawobprmPStyBwjPmuJXg2",
    "dateTime": {
      "_seconds": 1751616000,
      "_nanoseconds": 0
    },
    "duration": 30,
    "timeSlot": "10:00",
    "status": "CONFIRMED",
    "roomId": "110463"
  },
  {
    "id": "cWMVGtCRWVeAb9MSkzer",
    "proId": "RD6p6iddC6XggWisjQSfzIkEm782",
    "clientId": "bSdsZwvvVnNUybmarOXTpuXq4l82",
    "dateTime": {
      "_seconds": 1751621400,
      "_nanoseconds": 0
    },
    "duration": 30,
    "timeSlot": "11:30",
    "status": "CONFIRMED",
    "roomId": "110836"
  },
  {
    "id": "xflFlHIdxb6bsXFLgYlR",
    "proId": "RD6p6iddC6XggWisjQSfzIkEm782",
    "clientId": "F8nlh9yawobprmPStyBwjPmuJXg2",
    "dateTime": {
      "_seconds": 1751637600,
      "_nanoseconds": 0
    },
    "duration": 30,
    "timeSlot": "16:00",
    "status": "CONFIRMED",
    "roomId": "226492",
    "remindersSent": {
      "15min": true,
      "5min": true,
      "2min": true,
      "endingSoon": true
    }
  },
  {
    "id": "lDI6bLRIvmh9YI7m8g95",
    "proId": "RD6p6iddC6XggWisjQSfzIkEm782",
    "clientId": "F8nlh9yawobprmPStyBwjPmuJXg2",
    "dateTime": {
      "_seconds": 1751871600,
      "_nanoseconds": 0
    },
    "duration": 30,
    "timeSlot": "09:00",
    "status": "CONFIRMED",
    "roomId": "960858"
  },
  {
    "id": "TO4pxnBIjWzAVyztOtcj",
    "proId": "RD6p6iddC6XggWisjQSfzIkEm782",
    "clientId": "F8nlh9yawobprmPStyBwjPmuJXg2",
    "dateTime": {
      "_seconds": 1751817600,
      "_nanoseconds": 439000000
    },
    "duration": 30000,
    "timeSlot": "18:00",
    "status": "CONFIRMED",
    "roomId": "816339"
  },
  {
    "id": "N6dxUhmy8cOCMWWwNSa8",
    "proId": "RD6p6iddC6XggWisjQSfzIkEm782",
    "clientId": "F8nlh9yawobprmPStyBwjPmuJXg2",
    "dateTime": {
      "_seconds": 1751898600,
      "_nanoseconds": 0
    },
    "duration": 30,
    "timeSlot": "16:30",
    "status": "CONFIRMED",
    "roomId": "234288",
    "remindersSent": {
      "15min": true,
      "5min": true,
      "2min": true,
      "endingSoon": true
    }
  },
  {
    "id": "1mOG5YpgZ6VbDHO0ZHWR",
    "proId": "RD6p6iddC6XggWisjQSfzIkEm782",
    "clientId": "bSdsZwvvVnNUybmarOXTpuXq4l82",
    "dateTime": {
      "_seconds": 1751895000,
      "_nanoseconds": 0
    },
    "duration": 30,
    "timeSlot": "15:30",
    "status": "CONFIRMED",
    "roomId": "404242",
    "remindersSent": {
      "endingSoon": true
    }
  }
]